odoo/addons/crm_sale_automatic_quotation/README.rst
odoo/addons/crm_sale_automatic_quotation/__init__.py
odoo/addons/crm_sale_automatic_quotation/__manifest__.py
odoo/addons/crm_sale_automatic_quotation/data/ir_config_parameter.xml
odoo/addons/crm_sale_automatic_quotation/data/mail_activity_type.xml
odoo/addons/crm_sale_automatic_quotation/i18n/es.po
odoo/addons/crm_sale_automatic_quotation/models/__init__.py
odoo/addons/crm_sale_automatic_quotation/models/crm_lead.py
odoo/addons/crm_sale_automatic_quotation/models/crm_stage.py
odoo/addons/crm_sale_automatic_quotation/models/sale_order_template.py
odoo/addons/crm_sale_automatic_quotation/security/ir.model.access.csv
odoo/addons/crm_sale_automatic_quotation/static/description/icon.png
odoo/addons/crm_sale_automatic_quotation/tests/__init__.py
odoo/addons/crm_sale_automatic_quotation/tests/test_crm_lead.py
odoo/addons/crm_sale_automatic_quotation/tests/test_crm_sale_automatic_quotation_wizard.py
odoo/addons/crm_sale_automatic_quotation/views/crm_lead_views.xml
odoo/addons/crm_sale_automatic_quotation/views/crm_stage_views.xml
odoo/addons/crm_sale_automatic_quotation/views/sale_order_template_views.xml
odoo/addons/crm_sale_automatic_quotation/wizards/__init__.py
odoo/addons/crm_sale_automatic_quotation/wizards/crm_sale_automatic_quotation_wizard.py
odoo/addons/crm_sale_automatic_quotation/wizards/crm_sale_automatic_quotation_wizard.xml
odoo_addon_crm_sale_automatic_quotation-18.0.1.0.0.1.dist-info/METADATA
odoo_addon_crm_sale_automatic_quotation-18.0.1.0.0.1.dist-info/WHEEL
odoo_addon_crm_sale_automatic_quotation-18.0.1.0.0.1.dist-info/top_level.txt
odoo_addon_crm_sale_automatic_quotation-18.0.1.0.0.1.dist-info/RECORD
